notebooks/seq/lfsr.v
module lfsr_4b (
    input wire clk,
    input wire nrst,
    output reg [3:0] lfsr
);
    always @(posedge clk or negedge nrst) begin
        if (!nrst)
            lfsr <= 4'b0001; // Non-zero seed
        else begin
            lfsr[0] <= lfsr[3];
            lfsr[1] <= lfsr[0];
            lfsr[2] <= lfsr[1] ^ lfsr[3];
            lfsr[3] <= lfsr[2];
        end
    end
endmodule

notebooks/seq/tb_lfsr.v
// Testbench for 4-bit Galois LFSR
`timescale 1ns/1ps

module tb_lfsr;
    reg clk;
    reg nrst;
    wire [3:0] lfsr;

    // Instantiate the LFSR module
    lfsr_4b uut (
        .clk(clk),
        .nrst(nrst),
        .lfsr(lfsr)
    );

    reg [3:0] expected_seq [0:14];
    integer i, errors;
    initial begin
        $dumpfile("tb_lfsr.vcd");
        $dumpvars(0, tb_lfsr);
        clk = 0;
        nrst = 0;
        // Expected sequence for seed 4'b0001 and taps at 4,3 (x^4 + x^3 + 1)
        expected_seq[0]  = 4'b0010;
        expected_seq[1]  = 4'b0100;
        expected_seq[2]  = 4'b1000;
        expected_seq[3]  = 4'b0101;
        expected_seq[4]  = 4'b1010;
        expected_seq[5]  = 4'b0001;
        expected_seq[6]  = 4'b0010;
        expected_seq[7]  = 4'b0100;
        expected_seq[8]  = 4'b1000;
        expected_seq[9]  = 4'b0101;
        expected_seq[10] = 4'b1010;
        expected_seq[11] = 4'b0001;
        expected_seq[12] = 4'b0010;
        expected_seq[13] = 4'b0100;
        expected_seq[14] = 4'b1000;

        #5 nrst = 1;
        errors = 0;
        for (i = 0; i < 15; i = i + 1) begin
            #5 clk = ~clk;
            #5 clk = ~clk;
            $display("Cycle %0d: lfsr = %b, expected = %b", i, lfsr, expected_seq[i]);
            if (lfsr !== expected_seq[i]) begin
                $display("ERROR: Mismatch at cycle %0d!", i);
                errors = errors + 1;
            end
        end
        if (errors == 0)
            $display("PASS: LFSR matches expected sequence.");
        else
            $display("FAIL: %0d mismatches detected.", errors);
        $finish;
    end
endmodule

notebooks/seq/tb_lfsr.vcd
$date
	Fri Sep  5 18:28:44 2025
$end
$version
	Icarus Verilog
$end
$timescale
	1ps
$end
$scope module tb_lfsr $end
$var wire 4 ! lfsr [3:0] $end
$var reg 1 " clk $end
$var reg 1 # nrst $end
$var integer 32 $ errors [31:0] $end
$var integer 32 % i [31:0] $end
$scope module uut $end
$var wire 1 " clk $end
$var wire 1 # nrst $end
$var reg 4 & lfsr [3:0] $end
$upscope $end
$upscope $end
$enddefinitions $end
$comment Show the parameter values. $end
$dumpall
$end
#0
$dumpvars
b1 &
bx %
bx $
0#
0"
b1 !
$end
#5000
b0 %
b0 $
1#
#10000
b10 !
b10 &
1"
#15000
b1 %
0"
#20000
b100 !
b100 &
1"
#25000
b10 %
0"
#30000
b1000 !
b1000 &
1"
#35000
b11 %
0"
#40000
b101 !
b101 &
1"
#45000
b100 %
0"
#50000
b1010 !
b1010 &
1"
#55000
b101 %
0"
#60000
b1 !
b1 &
1"
#65000
b110 %
0"
#70000
b10 !
b10 &
1"
#75000
b111 %
0"
#80000
b100 !
b100 &
1"
#85000
b1000 %
0"
#90000
b1000 !
b1000 &
1"
#95000
b1001 %
0"
#100000
b101 !
b101 &
1"
#105000
b1010 %
0"
#110000
b1010 !
b1010 &
1"
#115000
b1011 %
0"
#120000
b1 !
b1 &
1"
#125000
b1100 %
0"
#130000
b10 !
b10 &
1"
#135000
b1101 %
0"
#140000
b100 !
b100 &
1"
#145000
b1110 %
0"
#150000
b1000 !
b1000 &
1"
#155000
b1111 %
0"
